protpy/__init__.py
protpy/autocorrelation.py
protpy/composition.py
protpy/conjoint_triad.py
protpy/ctd.py
protpy/sequence_order.py
protpy/data/README.md
protpy/data/grantham-physiochemical-distance-matrix.json
protpy/data/schneider-wrede-physiochemical-distance-matrix.json
tests/__init__.py
tests/test_autocorrelation.py
tests/test_composition.py
tests/test_conjoint_triad.py
tests/test_ctd.py
tests/test_protpy.py
tests/test_sequence_order.py
protpy-1.2.0.dist-info/LICENSE
protpy-1.2.0.dist-info/METADATA
protpy-1.2.0.dist-info/WHEEL
protpy-1.2.0.dist-info/top_level.txt
protpy-1.2.0.dist-info/RECORD
