Metadata-Version: 2.1
Name: protpy
Version: 1.2.0
Summary: Python package for generating various biochemical, physiochemical and structural descriptors/features of protein sequences.
Home-page: https://github.com/amckenna41/protPy
Author: MIT
Author-email: amckenna41@qub.ac.uk
Maintainer: AJ McKenna
License: MIT
Download-URL: https://github.com/amckenna41/protPy/archive/refs/heads/main.zip
Keywords: bioinformatics,protein engineering,python,pypi,machine learning,aaindex,protein descriptors,physiochemical descriptors,biochemical descriptorsstructural descriptors,pySAR
Platform: UNKNOWN
Classifier: Development Status :: 5 - Production/Stable
Classifier: Environment :: Console
Classifier: Intended Audience :: Developers
Classifier: Intended Audience :: Science/Research
Classifier: Intended Audience :: Healthcare Industry
Classifier: Intended Audience :: Information Technology
Classifier: License :: OSI Approved :: MIT License
Classifier: Natural Language :: English
Classifier: Programming Language :: Python :: 3.8
Classifier: Programming Language :: Python :: 3.9
Classifier: Programming Language :: Python :: 3.10
Classifier: Programming Language :: Python :: Implementation :: PyPy
Classifier: Programming Language :: Python :: 3 :: Only
Classifier: Topic :: Scientific/Engineering :: Bio-Informatics
Classifier: Topic :: Scientific/Engineering :: Medical Science Apps.
Classifier: Topic :: Scientific/Engineering :: Mathematics
Classifier: Topic :: Software Development :: Libraries :: Python Modules
Requires-Python: >=3.6
License-File: LICENSE
Requires-Dist: aaindex
Requires-Dist: numpy
Requires-Dist: pandas
Requires-Dist: varname
Provides-Extra: docs
Requires-Dist: sphinx ; extra == 'docs'
Provides-Extra: test
Requires-Dist: pytest ; extra == 'test'
Requires-Dist: pytest-cov ; extra == 'test'
Requires-Dist: pytest-flake8 ; extra == 'test'
Requires-Dist: pytest-timeout ; extra == 'test'
Provides-Extra: test_suite
Requires-Dist: tests ; extra == 'test_suite'
